whoop_data/__init__.py
whoop_data/client.py
whoop_data/constants.py
whoop_data/data.py
whoop_data/endpoints.py
whoop_data/logger.py
whoop_data-1.0.0.dist-info/METADATA
whoop_data-1.0.0.dist-info/WHEEL
whoop_data-1.0.0.dist-info/top_level.txt
whoop_data-1.0.0.dist-info/RECORD
