Metadata-Version: 2.4
Name: whoop-data
Version: 1.0.0
Summary: Extract sleep and heart rate data from Whoop WebApp API (unofficial)
Author-email: Juraj Vasek <jjursk@pm.me>
License-Expression: MIT
Project-URL: Homepage, https://github.com/jjur/whoop-sleep-HR-data-api
Classifier: Programming Language :: Python :: 3
Classifier: Operating System :: OS Independent
Requires-Python: >=3.6
Requires-Dist: requests>=2.25.0
Requires-Dist: python-dotenv>=0.15.0
